curvit/__init__.py
curvit/check_curvit_variability_V.0.4.py
curvit/curvit.py
curvit/profile_curvit.py
curvit/test_curvit.py
curvit-1.7.2.dist-info/LICENSE
curvit-1.7.2.dist-info/METADATA
curvit-1.7.2.dist-info/WHEEL
curvit-1.7.2.dist-info/top_level.txt
curvit-1.7.2.dist-info/RECORD
