Metadata-Version: 2.1
Name: curvit
Version: 1.7.2
Summary: light curves from UVIT data
Home-page: https://github.com/prajwel/curvit
Author: Prajwel Joseph
Author-email: prajwel.joseph@gmail.com
Classifier: Programming Language :: Python :: 3
Classifier: License :: OSI Approved :: Apache Software License
Classifier: Operating System :: OS Independent
Requires-Python: >=3.6
License-File: LICENSE
Requires-Dist: numpy
Requires-Dist: matplotlib
Requires-Dist: astropy
Requires-Dist: photutils
Requires-Dist: scipy
Requires-Dist: scikit-image
Requires-Dist: aafitrans
Requires-Dist: astroquery
